tinyturret/__init__.py
tinyturret/admin.py
tinyturret/apps.py
tinyturret/base_settings.py
tinyturret/cli.py
tinyturret/db_models.py
tinyturret/middleware.py
tinyturret/models.py
tinyturret/settings.py
tinyturret/urls.py
tinyturret/utils.py
tinyturret/views.py
tinyturret/management/__init__.py
tinyturret/management/commands/__init__.py
tinyturret/management/commands/tinyturret.py
tinyturret/storage_backends/__init__.py
tinyturret/storage_backends/base_backend.py
tinyturret/storage_backends/django_cache_store.py
tinyturret/storage_backends/django_db_store.py
tinyturret/storage_backends/shelve_store.py
tiny_turret-0.0.1.dist-info/LICENSE
tiny_turret-0.0.1.dist-info/METADATA
tiny_turret-0.0.1.dist-info/WHEEL
tiny_turret-0.0.1.dist-info/entry_points.txt
tiny_turret-0.0.1.dist-info/top_level.txt
tiny_turret-0.0.1.dist-info/RECORD
