Metadata-Version: 2.1
Name: tiny-turret
Version: 0.0.1
Summary: Tiny django exception handler
Home-page: https://github.com/jacqueswww/tiny-turret
Author: Tiny Turret Team
Classifier: Framework :: Django
Classifier: Intended Audience :: Developers
Classifier: Topic :: Software Development
License-File: LICENSE
Requires-Dist: Django>=2.0.0
Requires-Dist: filelock>=3.16.1
Requires-Dist: tabulate>=0.9.0
Requires-Dist: tblib==3.0.0
Provides-Extra: test
Requires-Dist: pytest; extra == "test"
